net_device_conn/__init__.py
net_device_conn/drivers/__init__.py
net_device_conn/drivers/cisco/__init__.py
net_device_conn/drivers/cisco/cisco_ios.py
net_device_conn/drivers/cisco/cisco_nxos.py
net_device_conn/drivers/f5/__init__.py
net_device_conn/drivers/f5/f5_base.py
net_device_conn-0.1.0.dist-info/licenses/LICENSE
net_device_conn-0.1.0.dist-info/METADATA
net_device_conn-0.1.0.dist-info/WHEEL
net_device_conn-0.1.0.dist-info/top_level.txt
net_device_conn-0.1.0.dist-info/RECORD
