Metadata-Version: 2.4
Name: net_device_conn
Version: 0.1.0
Summary: Another network connection project using netmiko
Author-email: Larry Zhu <larry.lan.zhu@gmail.com>
License-Expression: MIT
Project-URL: Repository, https://github.com/myusernamehasbeentaken/net-device-conn
Keywords: network,client,ssh
Classifier: Programming Language :: Python :: 3.9
Classifier: Operating System :: OS Independent
Requires-Python: >=3.9
License-File: LICENSE
Requires-Dist: netmiko>=4.5.0
Dynamic: license-file
